unichat/__init__.py
unichat/api_helper.py
unichat/chat_helper.py
unichat/models.py
unichat/unichat.py
unichat-4.1.30.dist-info/licenses/LICENSE
unichat-4.1.30.dist-info/METADATA
unichat-4.1.30.dist-info/WHEEL
unichat-4.1.30.dist-info/top_level.txt
unichat-4.1.30.dist-info/RECORD
