Metadata-Version: 2.4
Name: unichat
Version: 4.1.30
Summary: Universal API chat Python client for OpenAI, MistralAI, Anthropic, xAI, Google AI, or any OpenAI SDK LLM provider.
Author-email: Stefan <versed_info0w@icloud.com>
License-Expression: MIT
Project-URL: Repository, https://github.com/amidabuddha/unichat
Requires-Python: >=3.11
License-File: LICENSE
Requires-Dist: anthropic~=0.69.0
Requires-Dist: mistralai~=1.9.10
Requires-Dist: openai~=1.109.1
Dynamic: license-file
